hedera_mirror_sdk/__init__.py
hedera_mirror_sdk/error.py
hedera_mirror_sdk/api_resources/__init__.py
hedera_mirror_sdk/api_resources/api_requester.py
hedera_mirror_sdk/api_resources/mixins.py
hedera_mirror_sdk/api_resources/abstract/__init__.py
hedera_mirror_sdk/api_resources/abstract/domain.py
hedera_mirror_sdk/rest/__init__.py
hedera_mirror_sdk/rest/account/__init__.py
hedera_mirror_sdk/rest/block/__init__.py
hedera_mirror_sdk/rest/network/__init__.py
hedera_mirror_sdk/rest/schedule_transaction/__init__.py
hedera_mirror_sdk/rest/smart_contract/__init__.py
hedera_mirror_sdk/rest/state_proof_alpha/__init__.py
hedera_mirror_sdk/rest/token/__init__.py
hedera_mirror_sdk/rest/topic/__init__.py
hedera_mirror_sdk/rest/transaction/__init__.py
hedera_mirror_sdk-0.0.6.dist-info/LICENSE
hedera_mirror_sdk-0.0.6.dist-info/METADATA
hedera_mirror_sdk-0.0.6.dist-info/WHEEL
hedera_mirror_sdk-0.0.6.dist-info/top_level.txt
hedera_mirror_sdk-0.0.6.dist-info/RECORD
