Metadata-Version: 2.1
Name: hedera-mirror-sdk
Version: 0.0.6
Summary: This is a simple Python library to facilitate the usage of the Hedera mirror node API
Home-page: https://github.com/bobby-didcoding/hedera-mirror-sdk
Author: Bobby Stearman
Author-email: bobby@didcoding.com
Project-URL: Bug Tracker, https://github.com/bobby-didcoding/hedera-mirror-sdk/issues
Classifier: Programming Language :: Python :: 3
Classifier: License :: OSI Approved :: BSD License
Classifier: Operating System :: OS Independent
Requires-Python: >=3.6
License-File: LICENSE
Requires-Dist: requests (>=2.28.0)
Requires-Dist: six (>=1.16.0)
